{
  "base": {
    "name": "深圳政务信息可视化展示",             
    "url": "",          
    "desc": "深圳政务信息资源数据可视化展示项目",                           
    "mobile":false,                       
    "scene":false                         
  },
  "schedule": {
    "status": "已完成",                  
    "actualStartTime": "2017-10-31",    
    "actualEndTime": "2017-12-22",      
    "estimatedStartTime": "2017-10-16", 
    "estimatedEndTime": "2017-12-31",   
    "process": 100,                      
    "delay": false,                      
    "technology":["jquery","vue","element"],
    "pages":124,
    "score":5
  },
  "resources": {
    "demander": "粤数",                     
    "type":"合资公司",				                  
    "manager":"王鹏",                   
    "charge": "邢玮",                   
    "affiliate": ["林源"],
    "average":2
  },
  "bug": {
    "total": 22,                     
    "resolved": 22,                  
    "unsolved": 0                     
  },
  "others": {
    "remark": "后台管理模块：已完成。企业专题：进行接口优化。"                 
  }
}
